lnprototest/__init__.py
lnprototest/backend/__init__.py
lnprototest/backend/backend.py
lnprototest/backend/bitcoind.py
lnprototest/bitfield.py
lnprototest/clightning/__init__.py
lnprototest/clightning/clightning.py
lnprototest/clightning/requirements.txt
lnprototest/commit_tx.py
lnprototest/dummyrunner.py
lnprototest/errors.py
lnprototest/event.py
lnprototest/funding.py
lnprototest/keyset.py
lnprototest/namespace.py
lnprototest/proposals.py
lnprototest/runner.py
lnprototest/signature.py
lnprototest/stash/__init__.py
lnprototest/stash/stash.py
lnprototest/structure.py
lnprototest/utils/__init__.py
lnprototest/utils/bitcoin_utils.py
lnprototest/utils/ln_spec_utils.py
lnprototest/utils/utils.py
lnprototest-0.0.7.dist-info/LICENSE
lnprototest-0.0.7.dist-info/METADATA
lnprototest-0.0.7.dist-info/WHEEL
lnprototest-0.0.7.dist-info/RECORD
