Metadata-Version: 2.1
Name: lnprototest
Version: 0.0.7
Summary: Spec protocol tests for lightning network implementations
License: MIT
Author: Rusty Russell
Author-email: rusty@blockstream.com
Requires-Python: >=3.9,<4.0
Classifier: License :: OSI Approved :: MIT License
Classifier: Programming Language :: Python :: 3
Classifier: Programming Language :: Python :: 3.9
Classifier: Programming Language :: Python :: 3.10
Classifier: Programming Language :: Python :: 3.11
Classifier: Programming Language :: Python :: 3.12
Classifier: Programming Language :: Python :: 3.13
Requires-Dist: crc32c (>=2.2.post0,<3.0)
Requires-Dist: pyln-bolt1 (>=1.0.222,<2.0.0)
Requires-Dist: pyln-bolt2 (>=1.0.222,<2.0.0)
Requires-Dist: pyln-bolt4 (>=1.0.222,<2.0.0)
Requires-Dist: pyln-bolt7 (>=1.0.246,<2.0.0)
Requires-Dist: pyln-client (>=25.2.1,<26.0.0)
Requires-Dist: pyln-proto (>=23.05.2,<24.0.0)
Requires-Dist: pyln-testing (>=25.2.1,<26.0.0)
Requires-Dist: python-bitcoinlib (>=0.11.2,<0.12.0)
